{"commitInfo":{"timestamp":1765778961023,"operation":"WRITE","operationParameters":{"mode":"Overwrite","partitionBy":"[]"},"readVersion":3,"isolationLevel":"Serializable","isBlindAppend":false,"operationMetrics":{"numFiles":"2","numOutputRows":"300","numOutputBytes":"21685"},"engineInfo":"Apache-Spark/3.5.5 Delta-Lake/3.2.0","txnId":"1ef2d1ec-1005-4693-8b65-addce5e889fc"}}
{"add":{"path":"part-00000-a3d2294e-a283-4386-bfb3-ea4090c56e0f-c000.snappy.parquet","partitionValues":{},"size":12295,"modificationTime":1765778959744,"dataChange":true,"stats":"{\"numRecords\":208,\"minValues\":{\"vente_id\":1,\"client_id\":1,\"produit_id\":101,\"timestamp\":\"2025-12-14T09:21:37.010724\",\"quantite\":1,\"montant\":19.99,\"client_nom\":\"Anna Mueller\",\"produit_nom\":\"Casque audio\",\"categorie\":\"Electronique\",\"pays\":\"Allemagne\",\"segment\":\"Entreprise\",\"kafka_timestamp\":\"2025-12-14T09:21:37.272Z\",\"partition\":0,\"offset\":0,\"date_ingestion\":\"2025-12-15T06:08:19.226Z\",\"jour\":14,\"annee\":2025,\"mois\":12,\"jour_semaine\":\"Monday\",\"heure\":6,\"processed_at\":\"2025-12-15T06:09:16.183Z\"},\"maxValues\":{\"vente_id\":50,\"client_id\":5,\"produit_id\":105,\"timestamp\":\"2025-12-15T06:07:44.775142\",\"quantite\":3,\"montant\":2699.97,\"client_nom\":\"Paolo Rossi\",\"produit_nom\":\"Souris sans fil\",\"categorie\":\"Livre\",\"pays\":\"UK\",\"segment\":\"Particulier\",\"kafka_timestamp\":\"2025-12-15T06:07:44.775Z\",\"partition\":2,\"offset\":106,\"date_ingestion\":\"2025-12-15T06:08:19.226Z\",\"jour\":15,\"annee\":2025,\"mois\":12,\"jour_semaine\":\"Sunday\",\"heure\":9,\"processed_at\":\"2025-12-15T06:09:16.183Z\"},\"nullCount\":{\"vente_id\":0,\"client_id\":0,\"produit_id\":0,\"timestamp\":0,\"quantite\":0,\"montant\":0,\"client_nom\":0,\"produit_nom\":0,\"categorie\":0,\"pays\":0,\"segment\":0,\"kafka_timestamp\":0,\"partition\":0,\"offset\":0,\"date_ingestion\":0,\"jour\":0,\"annee\":0,\"mois\":0,\"jour_semaine\":0,\"heure\":0,\"processed_at\":0}}"}}
{"add":{"path":"part-00001-ad38a0cf-ea76-48f6-8aa4-ad84f88f816d-c000.snappy.parquet","partitionValues":{},"size":9390,"modificationTime":1765778959503,"dataChange":true,"stats":"{\"numRecords\":92,\"minValues\":{\"vente_id\":1,\"client_id\":1,\"produit_id\":101,\"timestamp\":\"2025-12-14T09:21:37.880250\",\"quantite\":1,\"montant\":19.99,\"client_nom\":\"Anna Mueller\",\"produit_nom\":\"Casque audio\",\"categorie\":\"Electronique\",\"pays\":\"Allemagne\",\"segment\":\"Entreprise\",\"kafka_timestamp\":\"2025-12-14T09:21:37.880Z\",\"partition\":1,\"offset\":0,\"date_ingestion\":\"2025-12-15T06:08:19.226Z\",\"jour\":14,\"annee\":2025,\"mois\":12,\"jour_semaine\":\"Monday\",\"heure\":6,\"processed_at\":\"2025-12-15T06:09:16.183Z\"},\"maxValues\":{\"vente_id\":50,\"client_id\":5,\"produit_id\":105,\"timestamp\":\"2025-12-15T06:07:43.563085\",\"quantite\":3,\"montant\":2699.97,\"client_nom\":\"Paolo Rossi\",\"produit_nom\":\"Souris sans fil\",\"categorie\":\"Livre\",\"pays\":\"UK\",\"segment\":\"Particulier\",\"kafka_timestamp\":\"2025-12-15T06:07:43.563Z\",\"partition\":1,\"offset\":91,\"date_ingestion\":\"2025-12-15T06:08:19.226Z\",\"jour\":15,\"annee\":2025,\"mois\":12,\"jour_semaine\":\"Sunday\",\"heure\":9,\"processed_at\":\"2025-12-15T06:09:16.183Z\"},\"nullCount\":{\"vente_id\":0,\"client_id\":0,\"produit_id\":0,\"timestamp\":0,\"quantite\":0,\"montant\":0,\"client_nom\":0,\"produit_nom\":0,\"categorie\":0,\"pays\":0,\"segment\":0,\"kafka_timestamp\":0,\"partition\":0,\"offset\":0,\"date_ingestion\":0,\"jour\":0,\"annee\":0,\"mois\":0,\"jour_semaine\":0,\"heure\":0,\"processed_at\":0}}"}}
{"remove":{"path":"part-00000-a3ead069-b08d-4b6b-a1f5-3113a7e3222d-c000.snappy.parquet","deletionTimestamp":1765778960970,"dataChange":true,"extendedFileMetadata":true,"partitionValues":{},"size":11406}}
{"remove":{"path":"part-00001-a6459afc-ee63-449d-9a5b-35728c03e9dc-c000.snappy.parquet","deletionTimestamp":1765778960970,"dataChange":true,"extendedFileMetadata":true,"partitionValues":{},"size":8990}}
