{"commitInfo":{"timestamp":1765779011258,"operation":"WRITE","operationParameters":{"mode":"Overwrite","partitionBy":"[]"},"readVersion":3,"isolationLevel":"Serializable","isBlindAppend":false,"operationMetrics":{"numFiles":"1","numOutputRows":"5","numOutputBytes":"1848"},"engineInfo":"Apache-Spark/3.5.5 Delta-Lake/3.2.0","txnId":"198880a7-5afc-45aa-8236-fcd6a774831f"}}
{"add":{"path":"part-00000-248a54c3-7850-469d-8cae-5411ea7dca8e-c000.snappy.parquet","partitionValues":{},"size":1848,"modificationTime":1765779010344,"dataChange":true,"stats":"{\"numRecords\":5,\"minValues\":{\"produit_nom\":\"Casque audio\",\"categorie\":\"Electronique\",\"ventes_count\":53,\"revenue_total\":2398.8,\"quantite_moyenne\":1.83},\"maxValues\":{\"produit_nom\":\"Souris sans fil\",\"categorie\":\"Livre\",\"ventes_count\":65,\"revenue_total\":105298.83,\"quantite_moyenne\":2.13},\"nullCount\":{\"produit_nom\":0,\"categorie\":0,\"ventes_count\":0,\"revenue_total\":0,\"quantite_moyenne\":0}}"}}
{"remove":{"path":"part-00000-abf5f424-43ac-4161-b497-f6b9b7b2fd22-c000.snappy.parquet","deletionTimestamp":1765779011255,"dataChange":true,"extendedFileMetadata":true,"partitionValues":{},"size":1850}}
